odoo10_addon_website_event_snippet_calendar-10.0.1.0.2-nspkg.pth
odoo/addons/website_event_snippet_calendar/README.rst
odoo/addons/website_event_snippet_calendar/__init__.py
odoo/addons/website_event_snippet_calendar/__manifest__.py
odoo/addons/website_event_snippet_calendar/controllers/__init__.py
odoo/addons/website_event_snippet_calendar/controllers/main.py
odoo/addons/website_event_snippet_calendar/i18n/de.po
odoo/addons/website_event_snippet_calendar/i18n/es.po
odoo/addons/website_event_snippet_calendar/i18n/website_event_snippet_calendar.pot
odoo/addons/website_event_snippet_calendar/static/description/icon.png
odoo/addons/website_event_snippet_calendar/static/description/icon.svg
odoo/addons/website_event_snippet_calendar/static/lib/bootstrap-datetimepicker.js
odoo/addons/website_event_snippet_calendar/static/lib/bootstrap-datetimepicker.less
odoo/addons/website_event_snippet_calendar/static/src/css/style.less
odoo/addons/website_event_snippet_calendar/static/src/js/animation.js
odoo/addons/website_event_snippet_calendar/static/src/js/options.js
odoo/addons/website_event_snippet_calendar/static/src/xml/snippets.xml
odoo/addons/website_event_snippet_calendar/templates/assets.xml
odoo/addons/website_event_snippet_calendar/templates/embed.xml
odoo/addons/website_event_snippet_calendar/templates/snippets.xml
odoo10_addon_website_event_snippet_calendar-10.0.1.0.2.dist-info/METADATA
odoo10_addon_website_event_snippet_calendar-10.0.1.0.2.dist-info/WHEEL
odoo10_addon_website_event_snippet_calendar-10.0.1.0.2.dist-info/namespace_packages.txt
odoo10_addon_website_event_snippet_calendar-10.0.1.0.2.dist-info/top_level.txt
odoo10_addon_website_event_snippet_calendar-10.0.1.0.2.dist-info/RECORD
